cli.py
cocopye/__init__.py
cocopye/constants.py
cocopye/core.py
cocopye/histogram.py
cocopye/pfam.py
cocopye/matrices/__init__.py
cocopye/matrices/_numba_functions.py
cocopye/ui/__init__.py
cocopye/ui/config.py
cocopye/ui/config.toml
cocopye/ui/external/__init__.py
cocopye/ui/external/bin.py
cocopye/ui/external/data.py
cocopye/ui/terminal/__init__.py
cocopye/ui/web/__init__.py
cocopye/ui/web/server.py
cocopye/ui/web/tasks.py
cocopye/ui/web/static/example_data.zip
cocopye/ui/web/static/script.js
cocopye/ui/web/static/css/daisyui-4.3.1.css
cocopye/ui/web/static/css/daisyui_license.txt
cocopye/ui/web/static/css/tailwind-3.3.5.css
cocopye/ui/web/static/css/tailwind_license.txt
cocopye/ui/web/static/icons/Font-Awesome/LICENSE.txt
cocopye/ui/web/static/icons/Font-Awesome/book.svg
cocopye/ui/web/static/icons/Font-Awesome/github.svg
cocopye/ui/web/static/icons/bytesize-icons/LICENSE.md
cocopye/ui/web/static/icons/bytesize-icons/mail.svg
cocopye/ui/web/static/icons/simple-line-icons/LICENSE.md
cocopye/ui/web/static/icons/simple-line-icons/question.svg
cocopye/ui/web/templates/index.html
cocopye-0.5.0.dist-info/COPYING
cocopye-0.5.0.dist-info/METADATA
cocopye-0.5.0.dist-info/WHEEL
cocopye-0.5.0.dist-info/entry_points.txt
cocopye-0.5.0.dist-info/top_level.txt
cocopye-0.5.0.dist-info/RECORD
