Metadata-Version: 2.1
Name: cocopye
Version: 0.5.0
Summary: Feature-based prediction of genome quality indices
Author: Niklas Birth, Nicolina Leppich, Dr. Peter Meinicke
Maintainer-email: Niklas Birth <birth@posteo.de>
License: GPL-3.0-or-later
Project-URL: Homepage, https://cocopye.uni-goettingen.de
Project-URL: Source, https://github.com/gobics/cocopye
Project-URL: Documentation, https://github.com/gobics/cocopye/wiki
Keywords: bioinformatics,biology,microbiology,metagenomics,genome,genome quality
Classifier: Programming Language :: Python :: 3
Classifier: Intended Audience :: Science/Research
Classifier: License :: OSI Approved :: GNU General Public License v3 or later (GPLv3+)
Classifier: Development Status :: 4 - Beta
Requires-Python: >=3.8
License-File: COPYING
Requires-Dist: numpy >=1.23
Requires-Dist: numba >=0.56.4
Requires-Dist: biopython ==1.81
Requires-Dist: scikit-learn ==1.3.1
Requires-Dist: pandas
Requires-Dist: packaging
Requires-Dist: appdirs ~=1.4.4
Requires-Dist: tomlkit ~=0.11.6
Requires-Dist: requests ~=2.31.0
Requires-Dist: tqdm ~=4.65.0
Requires-Dist: numba-progress ==1.0.0
Provides-Extra: web
Requires-Dist: celery[redis] ~=5.3.1 ; extra == 'web'
Requires-Dist: uvicorn ~=0.22.0 ; extra == 'web'
Requires-Dist: fastapi ~=0.99.1 ; extra == 'web'
Requires-Dist: python-multipart ~=0.0.6 ; extra == 'web'
Requires-Dist: websockets ~=11.0.3 ; extra == 'web'
Requires-Dist: werkzeug ; extra == 'web'
Requires-Dist: Jinja2 ~=3.1.2 ; extra == 'web'
